my_happy_graphviz/__init__.py
my_happy_graphviz/dot_parser.py
my_happy_graphviz/pydot.py
my_happy_graphviz/version.py
my_happy_graphviz-1.4.27.dist-info/LICENSE
my_happy_graphviz-1.4.27.dist-info/METADATA
my_happy_graphviz-1.4.27.dist-info/WHEEL
my_happy_graphviz-1.4.27.dist-info/top_level.txt
my_happy_graphviz-1.4.27.dist-info/RECORD
