Metadata-Version: 2.1
Name: my-happy-graphviz
Version: 1.4.27
Summary: Python interface to Graphviz's Dot language
Home-page: https://github.com/ggservice007/my-happy-graphviz
Author: ggservice007
Author-email: ggservice007@126.com
License: Apache 2
Platform: UNKNOWN
Requires-Python: >=3.7.7
Requires-Dist: pyparsing (>=2.4.7)
